pygooglecloudutils/__init__.py
pygooglecloudutils/version.py
pygooglecloudutils-0.0.0.1.dist-info/LICENSE
pygooglecloudutils-0.0.0.1.dist-info/METADATA
pygooglecloudutils-0.0.0.1.dist-info/WHEEL
pygooglecloudutils-0.0.0.1.dist-info/top_level.txt
pygooglecloudutils-0.0.0.1.dist-info/RECORD
