Metadata-Version: 2.1
Name: pygooglecloudutils
Version: 0.0.0.1
Summary: A collection of utilities for interacting with Google Cloud Platform
Home-page: http://www.microchip.com
Author: Microchip Technology
Author-email: support@microchip.com
License: Microchip Technology Inc. Proprietary License
Platform: UNKNOWN
Classifier: Development Status :: 3 - Alpha
Classifier: Intended Audience :: Developers
Classifier: Topic :: Software Development :: Embedded Systems
Classifier: License :: Other/Proprietary License
Classifier: Programming Language :: Python :: 2
Classifier: Programming Language :: Python :: 2.7
Classifier: Programming Language :: Python :: 3
Classifier: Programming Language :: Python :: 3.6
Classifier: Operating System :: Microsoft :: Windows
Classifier: Operating System :: POSIX :: Linux
Classifier: Operating System :: MacOS
Provides-Extra: dev
Requires-Dist: pylint ; extra == 'dev'
Requires-Dist: mock ; extra == 'dev'
